kaiju_tasks/__init__.py
kaiju_tasks/gui.py
kaiju_tasks/services.py
kaiju_tasks/types.py
kaiju_tasks/tests/__init__.py
kaiju_tasks/tests/fixtures.py
kaiju_tasks/tests/test_tasks.py
kaiju_tasks-2.1.11.dist-info/LICENSE
kaiju_tasks-2.1.11.dist-info/METADATA
kaiju_tasks-2.1.11.dist-info/WHEEL
kaiju_tasks-2.1.11.dist-info/top_level.txt
kaiju_tasks-2.1.11.dist-info/RECORD
